{
	"globals": {
		"appName": "fullstack-nextjs-cdk-starter",
		"hosting": {
			"ghTokenName": "github-token",
			"ghOwner": "focusOtter",
			"repo": "fullstack-nextjs-cdk-starter"
		}
	},
	"main": {
		"stage": "prod",
		"env": {
			"account": "842537737558",
			"region": "us-east-1"
		}
	},
	"staging": {
		"stage": "staging",
		"env": {
			"account": "123",
			"region": "us-east-1"
		}
	},
	"develop": {
		"stage": "dev",
		"env": {
			"account": "842537737558",
			"region": "us-east-1"
		}
	}
}
